packageanil/__init__.py
packageanil/calculation.py
packageanil/setup.py
packageanil-0.2.dist-info/METADATA
packageanil-0.2.dist-info/WHEEL
packageanil-0.2.dist-info/top_level.txt
packageanil-0.2.dist-info/RECORD
