Metadata-Version: 2.1
Name: packageanil
Version: 0.2
Summary: this is code with anil package
Author: anil
